{"stem":"3,1","instances":[{"docId":"desc__paris_bnf_lat_8663","docUri":"desc__paris_bnf_lat_8663.html","score":3,"contexts":[{"form":"3,1","weight":"1","pos":166,"context":"...1899, p. LVIII. — Saxl, Verzeichnis <mark>3,1<\/mark>, p. XX. — Bernhard, Michael, ed...."},{"form":"3,1","weight":"1","pos":1065,"context":"Saxl, Verzeichnis <mark>3,1<\/mark>"},{"form":"3,1","weight":"1","pos":1078,"context":"...Mythologischer Illustrierter Handschriften Des Lateinischen Mittelalters. Vol. <mark>3,1<\/mark>: Handschriften in englischen Bibliotheken. Heidelberg: Winter..."}]},{"docId":"desc__london_bl_harley_2506","docUri":"desc__london_bl_harley_2506.html","score":3,"contexts":[{"form":"3,1","weight":"1","pos":251,"context":"Selected Bibliography:Saxl, Verzeichnis <mark>3,1<\/mark>, pp. 157-160. — Borst,..."},{"form":"3,1","weight":"1","pos":1216,"context":"Saxl, Verzeichnis <mark>3,1<\/mark>"},{"form":"3,1","weight":"1","pos":1229,"context":"...Mythologischer Illustrierter Handschriften Des Lateinischen Mittelalters. Vol. <mark>3,1<\/mark>: Handschriften in englischen Bibliotheken. Heidelberg: Winter..."}]},{"docId":"desc__london_bl_royal_13AXI","docUri":"desc__london_bl_royal_13AXI.html","score":3,"contexts":[{"form":"3,1","weight":"1","pos":315,"context":"...169, here 145. — Saxl, Verzeichnis <mark>3,1<\/mark>, pp. 197-98- — Gneuss, H. Handlist..."},{"form":"3,1","weight":"1","pos":1384,"context":"Saxl, Verzeichnis <mark>3,1<\/mark>"},{"form":"3,1","weight":"1","pos":1397,"context":"...Mythologischer Illustrierter Handschriften Des Lateinischen Mittelalters. Vol. <mark>3,1<\/mark>: Handschriften in englischen Bibliotheken. Heidelberg: Winter..."}]},{"docId":"desc__bamberg_sb_class_55","docUri":"desc__bamberg_sb_class_55.html","score":2,"contexts":[{"form":"3,1","weight":"1","pos":425,"context":"...p. 250. — Munk Olsen, L’ étude <mark>3,1<\/mark>, p. 38. — Toneatto, Lucio. Codices..."},{"form":"3,1","weight":"1","pos":1445,"context":"Munk Olsen, L’ étude <mark>3,1<\/mark>"}]}]}