{"stem":"3109","instances":[{"docId":"text__hyginus_astronomia","docUri":"text__hyginus_astronomia.html","score":1,"contexts":[{"form":"3109","weight":"1","pos":478,"context":"..., Biblioteca apostolica vaticana, Vat. lat. <mark>3109<\/mark> (s. XV)","fid":"d206e212"}]},{"docId":"text__revised_aratus_latinus","docUri":"text__revised_aratus_latinus.html","score":1,"contexts":[{"form":"3109","weight":"1","pos":192,"context":"..., Biblioteca apostolica vaticana, Vat. lat. <mark>3109<\/mark> (s. XV)","fid":"d223e185"}]}]}