{"stem":"601","instances":[{"docId":"desc__brussels_br_5413-22","docUri":"desc__brussels_br_5413-22.html","score":1,"contexts":[{"form":"601","weight":"1","pos":1021,"context":".... MGH Epp. aevi carol. (IV), pp. <mark>601<\/mark>-9. "}]},{"docId":"desc__paris_bnf_lat_13955","docUri":"desc__paris_bnf_lat_13955.html","score":1,"contexts":[{"form":"601","weight":"1","pos":2580,"context":"...: Teubner, 1874 (here pp. 588-<mark>601<\/mark>). "}]},{"docId":"text__anonymus_sangallensis","docUri":"text__anonymus_sangallensis.html","score":1,"contexts":[{"form":"601","weight":"1","pos":115,"context":"...Berlin: Weidmann, 1898, pp. 595-<mark>601<\/mark>. Hadravova, A. The Second Vatican Mythographer...."}]}]}