{"stem":"dardanum","instances":[{"docId":"desc__austin_hrc_29","docUri":"desc__austin_hrc_29.html","score":2,"contexts":[{"form":"Dardanum","weight":"1","pos":780,"context":"...100v-101v (Ps?)Jerome: Epistola ad <mark>Dardanum<\/mark> ›Epistula hieronimi ad dardanum de generibus musicorum incipit..."},{"form":"dardanum","weight":"1","pos":783,"context":"...Jerome: Epistola ad Dardanum ›Epistula hieronimi ad <mark>dardanum<\/mark> de generibus musicorum incipit cum interrogatione sua‹ Cogor..."}]}]}