{"stem":"divisi","instances":[{"docId":"desc__klosterneuburg_sb_685","docUri":"desc__klosterneuburg_sb_685.html","score":1,"contexts":[{"form":"divisis","weight":"1","pos":499,"context":"...signo uersetur mars annis ab inicio mundi per senarium <mark>divisis<\/mark> … — … memoratum semper inueniri planetam uirgo...."}]},{"docId":"desc__melk_sb_412","docUri":"desc__melk_sb_412.html","score":1,"contexts":[{"form":"divisis","weight":"1","pos":466,"context":"29-30 IQSVM Annis ab inicio mundi per senarium <mark>divisis<\/mark> … — … memoratum semper inveniri planetam virgo...."}]},{"docId":"listtitle","docUri":"listtitle.html","score":1,"contexts":[{"form":"divisis","weight":"1","pos":2797,"context":"...uersetur Mars: annis ab initio mundi per senarium <mark>divisis<\/mark> et annorum hunc numerum excedentium mensibus"}]}]}