{"stem":"invect","instances":[{"docId":"listtitle","docUri":"listtitle.html","score":2,"contexts":[{"form":"Invectives","weight":"1","pos":3166,"context":"...372-391. Novokhatko, Anna. The <mark>Invectives<\/mark> of Sallust and Cicero. Critical Edition with Introduction...","fid":"in_sallustium"},{"form":"Invectives","weight":"1","pos":3187,"context":"...Ps-Sallustius In Ciceronem Novokhatko, Anna. The <mark>Invectives<\/mark> of Sallust and Cicero. Critical Edition with Introduction...","fid":"in_ciceronem"}]}]}