{"stem":"lang","instances":[{"docId":"text__germanicus","docUri":"text__germanicus.html","score":2,"contexts":[{"form":"Lang","weight":"1","pos":403,"context":"...Germanicus, and the Poetics of Latin Translation. <mark>Lang<\/mark> Classical Studies. New York u.a.: Peter Lang,...","fid":"d189e149"},{"form":"Lang","weight":"1","pos":409,"context":".... Lang Classical Studies. New York u.a.: Peter <mark>Lang<\/mark>, 2004.","fid":"d189e149"}]},{"docId":"desc__london_bl_cotton_tib_b_v","docUri":"desc__london_bl_cotton_tib_b_v.html","score":1,"contexts":[{"form":"lang","weight":"1","pos":1124,"context":"...ab antimolima … — … cubita pid and feopra <mark>lang<\/mark>. "}]},{"docId":"desc__brussels_br_10615-10729","docUri":"desc__brussels_br_10615-10729.html","score":1,"contexts":[{"form":"Lang","weight":"1","pos":1521,"context":"...neuedition, Übersetzung und Kommentar. Bern: Peter <mark>Lang<\/mark>, 2011."}]},{"docId":"desc__einsiedeln_sb_338","docUri":"desc__einsiedeln_sb_338.html","score":1,"contexts":[{"form":"Lang","weight":"1","pos":342,"context":"...von Einsiedeln 996 - 1996, edited by Odo <mark>Lang<\/mark>, 93–181. München: Bayerische Benediktinerakademie,..."}]},{"docId":"desc__bern_bb_88","docUri":"desc__bern_bb_88.html","score":1,"contexts":[{"form":"Lang","weight":"1","pos":349,"context":"...Bern, pp. 107-130. Bern: <mark>Lang<\/mark>, 1953. — Bischoff, Kommentar, pp...."}]}]}