{"stem":"mensurantur","instances":[{"docId":"desc__london_bl_royal_13AXI","docUri":"desc__london_bl_royal_13AXI.html","score":2,"contexts":[{"form":"mensurantur","weight":"1","pos":493,"context":"...horis mensium and De singulis horis in die quomodo <mark>mensurantur<\/mark> cum pedibus with a table of moveable feasts (f...."},{"form":"mensurantur","weight":"1","pos":536,"context":"...(13v) ›Item de singulis horis in die quomodo <mark>mensurantur<\/mark> cum pedibus‹ Coniunge semper duos menses coequales …..."}]}]}