{"stem":"music","instances":[{"docId":"desc__vienna_onb_51","docUri":"desc__vienna_onb_51.html","score":3,"contexts":[{"form":"music","weight":"1","pos":44,"context":"Miscellany on <mark>music<\/mark>, geometry and astronomy"},{"form":"Musical","weight":"1","pos":190,"context":"1r-2r <mark>Musical<\/mark> diagrams for the diapason and monochord. Bifolium (..."},{"form":"musice","weight":"1","pos":269,"context":"...artis musicae ›In nomine domini incipiunt Guidonis versus de <mark>musice<\/mark> explanatione suique nominis ordine‹ Gymnasio musas placuit reuocare..."}]},{"docId":"desc__paris_bnf_lat_13955","docUri":"desc__paris_bnf_lat_13955.html","score":1,"contexts":[{"form":"Music","weight":"1","pos":822,"context":"...sources musicales. Vol. 3. The theory of <mark>Music<\/mark>: From the Carolingian Era up to 1400...."}]},{"docId":"desc__bav_reg_lat_1260","docUri":"desc__bav_reg_lat_1260.html","score":1,"contexts":[{"form":"musical","weight":"1","pos":561,"context":"...Priscianus. Added probably in the 11th century with <mark>musical<\/mark> neumes. "}]}]}