{"stem":"offer","instances":[{"docId":"text__aratus_latinus","docUri":"text__aratus_latinus.html","score":1,"contexts":[{"form":"offering","weight":"1","pos":331,"context":"...shows the Greek and Latin versions side by side <mark>offering<\/mark> the possibility to compare the translation with what may...","fid":"d36e111"}]},{"docId":"text__de_ordine","docUri":"text__de_ordine.html","score":1,"contexts":[{"form":"offered","weight":"1","pos":125,"context":"...the 42 constellations, the author of the text <mark>offered<\/mark> a short introduction to the topic, explaining that...","fid":"d104e84"}]}]}