{"stem":"pritchard","instances":[{"docId":"listtitle","docUri":"listtitle.html","score":1,"contexts":[{"form":"Pritchard","weight":"1","pos":836,"context":"<mark>Pritchard<\/mark>, T. \"The Collatio Alexandri et Dindimi: A..."}]},{"docId":"desc__paris_bnf_lat_7886","docUri":"desc__paris_bnf_lat_7886.html","score":1,"contexts":[{"form":"Pritchard","weight":"1","pos":470,"context":"...Mediaevalia, 15 (1954): 124-9. T. <mark>Pritchard<\/mark>, \"The Collatio Alexandri et Dindimi: A Revised..."}]}]}