{"stem":"rectangular","instances":[{"docId":"desc__strasbourg_bnu_326","docUri":"desc__strasbourg_bnu_326.html","score":1,"contexts":[{"form":"rectangular","weight":"1","pos":1128,"context":"123r On f.123r a <mark>rectangular<\/mark> diagram of the planetary latitudes. "}]},{"docId":"desc__vienna_onb_12600","docUri":"desc__vienna_onb_12600.html","score":1,"contexts":[{"form":"rectangular","weight":"1","pos":1337,"context":"...human heads with wings. In the middle a <mark>rectangular<\/mark> with the four elements and world directions on each..."}]},{"docId":"desc__london_bl_harley_3595","docUri":"desc__london_bl_harley_3595.html","score":1,"contexts":[{"form":"rectangulars","weight":"1","pos":334,"context":"...subiecimus. On f. 48v a diagram with four <mark>rectangulars<\/mark> &gt; geometrica, &gt; arithmetica, &gt; armonica,..."}]},{"docId":"desc__rouen_bm_26","docUri":"desc__rouen_bm_26.html","score":1,"contexts":[{"form":"rectangular","weight":"1","pos":254,"context":"...sunt... 30r-v has a cut in a <mark>rectangular<\/mark> shape not affecting the text, foliation applyed after..."}]}]}