{"stem":"specif","instances":[{"docId":"desc__london_bl_harley_3595","docUri":"desc__london_bl_harley_3595.html","score":1,"contexts":[{"form":"Specific","weight":"1","pos":273,"context":"...: st, &amp; as well as e-caudata. <mark>Specific<\/mark> letters: &gt; a with an upright stroke and..."}]},{"docId":"desc__amiens_bm_222","docUri":"desc__amiens_bm_222.html","score":1,"contexts":[{"form":"specifically","weight":"1","pos":328,"context":"...illustrate the first chapter of Bede's DNR and more <mark>specifically<\/mark> the expression &gt; quadriformiratione. "}]},{"docId":"desc__paris_bnf_lat_7299a","docUri":"desc__paris_bnf_lat_7299a.html","score":1,"contexts":[{"form":"specifically","weight":"1","pos":171,"context":"...Olsen 1985), Limoges area (Folkerts) more <mark>specifically<\/mark> Abbey of Solignac (Borst) or Saint-..."}]}]}