{"stem":"stadtbibliothek","instances":[{"docId":"desc__schaffhausen_sb_min_61","docUri":"desc__schaffhausen_sb_min_61.html","score":2,"contexts":[{"form":"Stadtbibliothek","weight":"1","pos":36,"context":"Schaffhausen, <mark>Stadtbibliothek<\/mark>, Ministerialis 61","fid":"d3192"},{"form":"Stadtbibliothek","weight":"1","pos":534,"context":"...How to quote: Ivana Dobcheva, 'Schaffhausen, <mark>Stadtbibliothek<\/mark>, Ministerialis 61 - Aratea Digital' (https:\/\/...","fid":"d3192"}]},{"docId":"index-mss","docUri":"index-mss.html","score":1,"contexts":[{"form":"Stadtbibliothek","weight":"1","pos":359,"context":"Schaffhausen, <mark>Stadtbibliothek<\/mark>, Ministerialis 61"}]},{"docId":"text__de_signis_caeli","docUri":"text__de_signis_caeli.html","score":1,"contexts":[{"form":"Stadtbibliothek","weight":"1","pos":264,"context":"Schaffhausen, <mark>Stadtbibliothek<\/mark>, Ministerialis 61","fid":"d138e200"}]},{"docId":"text__excerptum","docUri":"text__excerptum.html","score":1,"contexts":[{"form":"Stadtbibliothek","weight":"1","pos":287,"context":"Schaffhausen, <mark>Stadtbibliothek<\/mark>, Ministerialis 61","fid":"d172e243"}]}]}