{"stem":"tardior","instances":[{"docId":"desc__paris_bnf_lat_12957","docUri":"desc__paris_bnf_lat_12957.html","score":1,"contexts":[{"form":"tardior","weight":"1","pos":1188,"context":"...sidus super hoc saturnia stella celsior his cunctis et <mark>tardior<\/mark> omnibus astris. Explicit: Remarks: written visibly..."}]},{"docId":"desc__paris_bnf_lat_12117","docUri":"desc__paris_bnf_lat_12117.html","score":1,"contexts":[{"form":"tardior","weight":"1","pos":1472,"context":"...uertuntur et anguis … — … Celsior his saturnus <mark>tardior<\/mark> omnibus astris. "}]},{"docId":"desc__london_bl_harley_2506","docUri":"desc__london_bl_harley_2506.html","score":1,"contexts":[{"form":"tardior","weight":"1","pos":393,"context":"...uertuntur et anguis … — … Celsior his saturnus <mark>tardior<\/mark> omnibus astris. "}]},{"docId":"desc__aberystwyth_nlw_735c","docUri":"desc__aberystwyth_nlw_735c.html","score":1,"contexts":[{"form":"tardior","weight":"1","pos":762,"context":"...uertuntur et anguis … — … Celsior his saturnus <mark>tardior<\/mark> omnibus astris. "}]}]}