{"stem":"uesperi","instances":[{"docId":"desc__boulogne-sur-mer_bm_188","docUri":"desc__boulogne-sur-mer_bm_188.html","score":1,"contexts":[{"form":"uesperi","weight":"1","pos":541,"context":"...II. Non. Januari or &gt; In attica uergilię <mark>uesperi<\/mark> occultantur for III. Non. Aprili. There..."}]},{"docId":"desc__paris_bnf_lat_5543","docUri":"desc__paris_bnf_lat_5543.html","score":1,"contexts":[{"form":"uesperi","weight":"1","pos":996,"context":"...as in fol. 96v : 'in attica uergiliae <mark>uesperi<\/mark> occultantur' - IIII N apr 'orion et gladius eius..."}]}]}