{"stem":"vulgari","instances":[{"docId":"desc__paris_bnf_lat_12117","docUri":"desc__paris_bnf_lat_12117.html","score":2,"contexts":[{"form":"vulgaris","weight":"1","pos":1429,"context":"...148r-160r Abbo of Fleury: Computus <mark>vulgaris<\/mark> Computus vulgaris qui dicitur ephemerida de luna "},{"form":"vulgaris","weight":"1","pos":1431,"context":"...160r Abbo of Fleury: Computus vulgaris Computus <mark>vulgaris<\/mark> qui dicitur ephemerida de luna "}]},{"docId":"listtitle","docUri":"listtitle.html","score":1,"contexts":[{"form":"vulgaris","weight":"1","pos":1030,"context":"Computus <mark>vulgaris<\/mark> qui dicitur Ephemeris","fid":"computus_vulgaris"}]},{"docId":"desc__vienna_onb_12600","docUri":"desc__vienna_onb_12600.html","score":1,"contexts":[{"form":"vulgaris","weight":"1","pos":1469,"context":"31v Abbo Floriacensis. Excerpt from Computus <mark>vulgaris<\/mark>. Efemeris uel ephemerida est subputatio singularum dierum…..."}]}]}